doxcli/__init__.py
doxcli/driver.py
doxcli/utils.py
dox_cli-1.0.11.dist-info/LICENSE
dox_cli-1.0.11.dist-info/METADATA
dox_cli-1.0.11.dist-info/WHEEL
dox_cli-1.0.11.dist-info/entry_points.txt
dox_cli-1.0.11.dist-info/top_level.txt
dox_cli-1.0.11.dist-info/RECORD
