Metadata-Version: 2.1
Name: dox-cli
Version: 1.0.11
Summary: Cli to create project structure
Author: Bijay Das <imbijaydas@gmail.com>
License: MIT License
Project-URL: Source, https://github.com/bijaydas/dox-cli
Requires-Python: >=3.7
License-File: LICENSE
